{
  "surah": {
    "id": "97",
    "surahNumber": 97,
    "slug": "al-qadr",
    "nameArabic": "القدر",
    "nameLatin": "Al-Qadr",
    "nameBosnian": "El-Kadr",
    "revelationType": "meccan",
    "ayahCount": 5
  },
  "ayahs": [
    {
      "id": "97:1",
      "ayahNumber": 1,
      "ayahNumberGlobal": 6126,
      "juz": 30,
      "page": 598,
      "arabicText": "إِنَّآ أَنزَلْنَـٰهُ فِى لَيْلَةِ ٱلْقَدْرِ",
      "transliteration": "Inna anzalnahu fee laylatialqadr",
      "translationBosnian": "Mi smo ga počeli objavljivati u Noći Kadr –",
      "tajwidSegments": [
        {
          "text": "إِنَّآ أَنزَلْنَـٰهُ فِى لَيْلَةِ ٱلْقَدْرِ",
          "rule": "normal"
        }
      ],
      "audio": {
        "reciterId": "mishary-alafasy",
        "url": "/audio/mishary-alafasy/097001.mp3",
        "durationMs": 0
      }
    },
    {
      "id": "97:2",
      "ayahNumber": 2,
      "ayahNumberGlobal": 6127,
      "juz": 30,
      "page": 598,
      "arabicText": "وَمَآ أَدْرَىٰكَ مَا لَيْلَةُ ٱلْقَدْرِ",
      "transliteration": "Wama adraka ma laylatualqadr",
      "translationBosnian": "a šta ti misliš šta je Noć Kadr?",
      "tajwidSegments": [
        {
          "text": "وَمَ",
          "rule": "normal"
        },
        {
          "text": "آ",
          "rule": "mad"
        },
        {
          "text": " أَ",
          "rule": "normal"
        },
        {
          "text": "دْ",
          "rule": "qalqalah"
        },
        {
          "text": "رَى",
          "rule": "normal"
        },
        {
          "text": "ٰ",
          "rule": "mad"
        },
        {
          "text": "كَ مَا لَيْلَةُ ",
          "rule": "normal"
        },
        {
          "text": "ٱ",
          "rule": "normal"
        },
        {
          "text": "لْقَ",
          "rule": "normal"
        },
        {
          "text": "دْ",
          "rule": "qalqalah"
        },
        {
          "text": "رِ",
          "rule": "normal"
        }
      ],
      "audio": {
        "reciterId": "mishary-alafasy",
        "url": "/audio/mishary-alafasy/097002.mp3",
        "durationMs": 0
      }
    },
    {
      "id": "97:3",
      "ayahNumber": 3,
      "ayahNumberGlobal": 6128,
      "juz": 30,
      "page": 598,
      "arabicText": "لَيْلَةُ ٱلْقَدْرِ خَيْرٌ مِّنْ أَلْفِ شَهْرٍ",
      "transliteration": "Laylatu alqadri khayrun min alfi shahr",
      "translationBosnian": "Noć Kadr je bolja od hiljadu mjeseci –",
      "tajwidSegments": [
        {
          "text": "لَيْلَةُ ",
          "rule": "normal"
        },
        {
          "text": "ٱ",
          "rule": "normal"
        },
        {
          "text": "لْقَ",
          "rule": "normal"
        },
        {
          "text": "دْ",
          "rule": "qalqalah"
        },
        {
          "text": "رِ خَيْر",
          "rule": "normal"
        },
        {
          "text": "ٌ مِّ",
          "rule": "ghunnah"
        },
        {
          "text": "نْ أَلْفِ شَهْرٍ",
          "rule": "normal"
        }
      ],
      "audio": {
        "reciterId": "mishary-alafasy",
        "url": "/audio/mishary-alafasy/097003.mp3",
        "durationMs": 0
      }
    },
    {
      "id": "97:4",
      "ayahNumber": 4,
      "ayahNumberGlobal": 6129,
      "juz": 30,
      "page": 598,
      "arabicText": "تَنَزَّلُ ٱلْمَلَـٰٓئِكَةُ وَٱلرُّوحُ فِيهَا بِإِذْنِ رَبِّهِم مِّن كُلِّ أَمْرٍ",
      "transliteration": "Tanazzalu almala-ikatu warroohufeeha bi-ithni rabbihim min kulli amr",
      "translationBosnian": "meleki i Džibril, s dozvolom Gospodara svoga, spuštaju se u njoj zbog odluke svake,",
      "tajwidSegments": [
        {
          "text": "تَنَزَّلُ ",
          "rule": "normal"
        },
        {
          "text": "ٱ",
          "rule": "normal"
        },
        {
          "text": "لْمَلَ",
          "rule": "normal"
        },
        {
          "text": "ـٰ",
          "rule": "mad"
        },
        {
          "text": "ٓئِكَةُ و",
          "rule": "normal"
        },
        {
          "text": "َ",
          "rule": "normal"
        },
        {
          "text": "ٱ",
          "rule": "normal"
        },
        {
          "text": "لرُّوحُ فِيهَا بِإِذْنِ رَبِّه",
          "rule": "normal"
        },
        {
          "text": "ِم مّ",
          "rule": "normal"
        },
        {
          "text": "ِن ك",
          "rule": "ikhfa"
        },
        {
          "text": "ُلِّ أَمْرٍ",
          "rule": "normal"
        }
      ],
      "audio": {
        "reciterId": "mishary-alafasy",
        "url": "/audio/mishary-alafasy/097004.mp3",
        "durationMs": 0
      }
    },
    {
      "id": "97:5",
      "ayahNumber": 5,
      "ayahNumberGlobal": 6130,
      "juz": 30,
      "page": 598,
      "arabicText": "سَلَـٰمٌ هِىَ حَتَّىٰ مَطْلَعِ ٱلْفَجْرِ",
      "transliteration": "Salamun hiya hatta matlaAAialfajr",
      "translationBosnian": "sigurnost je u njoj sve dok zora ne svane.",
      "tajwidSegments": [
        {
          "text": "سَلَ",
          "rule": "normal"
        },
        {
          "text": "ـ",
          "rule": "mad"
        },
        {
          "text": "ٰمٌ هِىَ حَتَّىٰ م",
          "rule": "normal"
        },
        {
          "text": "َط",
          "rule": "qalqalah"
        },
        {
          "text": "ْلَعِ",
          "rule": "normal"
        },
        {
          "text": " ",
          "rule": "normal"
        },
        {
          "text": "ٱلْف",
          "rule": "normal"
        },
        {
          "text": "َج",
          "rule": "qalqalah"
        },
        {
          "text": "ْرِ",
          "rule": "normal"
        }
      ],
      "audio": {
        "reciterId": "mishary-alafasy",
        "url": "/audio/mishary-alafasy/097005.mp3",
        "durationMs": 0
      }
    }
  ]
}